fastexcel/__init__.py
fastexcel/_fastexcel.abi3.so
fastexcel/_fastexcel.pyi
fastexcel/py.typed
fastexcel_rw-0.15.0.dist-info/METADATA
fastexcel_rw-0.15.0.dist-info/WHEEL
fastexcel_rw-0.15.0.dist-info/licenses/LICENSE
fastexcel_rw-0.15.0.dist-info/RECORD
