Metadata-Version: 2.4
Name: fastexcel-rw
Version: 0.15.0
Classifier: Development Status :: 5 - Production/Stable
Classifier: License :: OSI Approved :: MIT License
Classifier: Operating System :: OS Independent
Classifier: Programming Language :: Rust
Classifier: Programming Language :: Python
Classifier: Programming Language :: Python :: 3
Classifier: Programming Language :: Python :: 3 :: Only
Classifier: Programming Language :: Python :: 3.9
Classifier: Programming Language :: Python :: 3.10
Classifier: Programming Language :: Python :: 3.11
Classifier: Programming Language :: Python :: 3.12
Classifier: Programming Language :: Python :: 3.13
Classifier: Programming Language :: Python :: Implementation :: CPython
Requires-Dist: pyarrow>=8.0.0
Requires-Dist: typing-extensions>=4.0.0 ; python_full_version < '3.10'
Requires-Dist: pandas>=1.4.4 ; extra == 'pandas'
Requires-Dist: polars>=0.16.14 ; extra == 'polars'
Provides-Extra: pandas
Provides-Extra: polars
License-File: LICENSE
Summary: A fast excel file reader and writer for Python, written in Rust
Keywords: excel,xlsx,arrow,python,rust
Home-Page: https://github.com/ToucanToco/fastexcel
Author: ToucanToco, bryanhan <bryanhan1001@gmail.com>
Author-email: ToucanToco, bryanhan <bryanhan1001@gmail.com>
License: MIT
Requires-Python: >=3.9
Project-URL: Source Code, https://github.com/bryanhan1001/fastexcel-rw
Project-URL: Issues, https://github.com/bryanhan1001/fastexcel-rw
